vscode_gallery_api/__init__.py
vscode_gallery_api/client.py
vscode_gallery_api/models/__init__.py
vscode_gallery_api/models/gallery.py
vscode_gallery_api/models/vsix.py
vscode_gallery_api-0.9.1.dist-info/METADATA
vscode_gallery_api-0.9.1.dist-info/WHEEL
vscode_gallery_api-0.9.1.dist-info/top_level.txt
vscode_gallery_api-0.9.1.dist-info/RECORD
