Metadata-Version: 2.1
Name: vscode-gallery-api
Version: 0.9.1
Summary: VSCode gallery client and tools
Home-page: https://github.com/jose-pr/vscode-gallery-api
Author: Jose A.
Author-email: jose-pr@coqui.dev
License: UNKNOWN
Platform: UNKNOWN
Requires-Dist: requests
Requires-Dist: xmltodict
